{
  "overview": {
    "startDate": "2024-08-20",
    "endDate": "2024-11-18",
    "totalDays": 90,
    "avgDailyActiveUsers": 38,
    "peakDailyActiveUsers": 45,
    "lowDailyActiveUsers": 28
  },
  "dailyStats": [
    { "date": "2024-08-20", "activeUsers": 28, "totalSteps": 173600, "avgSteps": 6200, "workouts": 8, "nutritionLogs": 12, "sleepLogs": 15 },
    { "date": "2024-08-21", "activeUsers": 30, "totalSteps": 189000, "avgSteps": 6300, "workouts": 10, "nutritionLogs": 14, "sleepLogs": 18 },
    { "date": "2024-08-22", "activeUsers": 31, "totalSteps": 198200, "avgSteps": 6394, "workouts": 11, "nutritionLogs": 16, "sleepLogs": 20 },
    { "date": "2024-08-23", "activeUsers": 32, "totalSteps": 206400, "avgSteps": 6450, "workouts": 12, "nutritionLogs": 18, "sleepLogs": 22 },
    { "date": "2024-08-24", "activeUsers": 33, "totalSteps": 215820, "avgSteps": 6540, "workouts": 13, "nutritionLogs": 19, "sleepLogs": 24 },
    { "date": "2024-08-25", "activeUsers": 34, "totalSteps": 225440, "avgSteps": 6630, "workouts": 14, "nutritionLogs": 20, "sleepLogs": 25 },
    { "date": "2024-08-26", "activeUsers": 35, "totalSteps": 238000, "avgSteps": 6800, "workouts": 16, "nutritionLogs": 22, "sleepLogs": 27 },
    { "date": "2024-08-27", "activeUsers": 36, "totalSteps": 248400, "avgSteps": 6900, "workouts": 17, "nutritionLogs": 24, "sleepLogs": 28 },
    { "date": "2024-08-28", "activeUsers": 36, "totalSteps": 252000, "avgSteps": 7000, "workouts": 18, "nutritionLogs": 25, "sleepLogs": 29 },
    { "date": "2024-08-29", "activeUsers": 37, "totalSteps": 262920, "avgSteps": 7106, "workouts": 19, "nutritionLogs": 26, "sleepLogs": 30 },
    { "date": "2024-08-30", "activeUsers": 37, "totalSteps": 266980, "avgSteps": 7216, "workouts": 20, "nutritionLogs": 27, "sleepLogs": 31 },
    { "date": "2024-08-31", "activeUsers": 38, "totalSteps": 277540, "avgSteps": 7304, "workouts": 21, "nutritionLogs": 28, "sleepLogs": 32 },
    { "date": "2024-09-01", "activeUsers": 38, "totalSteps": 281160, "avgSteps": 7399, "workouts": 22, "nutritionLogs": 29, "sleepLogs": 33 },
    { "date": "2024-09-02", "activeUsers": 39, "totalSteps": 292110, "avgSteps": 7490, "workouts": 23, "nutritionLogs": 30, "sleepLogs": 34 },
    { "date": "2024-09-03", "activeUsers": 39, "totalSteps": 296400, "avgSteps": 7600, "workouts": 24, "nutritionLogs": 31, "sleepLogs": 35 },
    { "date": "2024-09-04", "activeUsers": 40, "totalSteps": 308000, "avgSteps": 7700, "workouts": 25, "nutritionLogs": 32, "sleepLogs": 36 },
    { "date": "2024-09-05", "activeUsers": 40, "totalSteps": 312000, "avgSteps": 7800, "workouts": 26, "nutritionLogs": 33, "sleepLogs": 37 },
    { "date": "2024-09-06", "activeUsers": 41, "totalSteps": 323950, "avgSteps": 7900, "workouts": 27, "nutritionLogs": 34, "sleepLogs": 38 },
    { "date": "2024-09-07", "activeUsers": 41, "totalSteps": 328000, "avgSteps": 8000, "workouts": 28, "nutritionLogs": 35, "sleepLogs": 39 },
    { "date": "2024-09-08", "activeUsers": 42, "totalSteps": 340200, "avgSteps": 8100, "workouts": 29, "nutritionLogs": 36, "sleepLogs": 40 },
    { "date": "2024-09-09", "activeUsers": 42, "totalSteps": 344400, "avgSteps": 8200, "workouts": 30, "nutritionLogs": 37, "sleepLogs": 41 },
    { "date": "2024-09-10", "activeUsers": 42, "totalSteps": 348600, "avgSteps": 8300, "workouts": 31, "nutritionLogs": 38, "sleepLogs": 42 },
    { "date": "2024-09-11", "activeUsers": 42, "totalSteps": 352800, "avgSteps": 8400, "workouts": 32, "nutritionLogs": 39, "sleepLogs": 42 },
    { "date": "2024-09-12", "activeUsers": 41, "totalSteps": 348750, "avgSteps": 8506, "workouts": 33, "nutritionLogs": 39, "sleepLogs": 41 },
    { "date": "2024-09-13", "activeUsers": 40, "totalSteps": 344000, "avgSteps": 8600, "workouts": 34, "nutritionLogs": 38, "sleepLogs": 40 },
    { "date": "2024-09-14", "activeUsers": 39, "totalSteps": 335400, "avgSteps": 8600, "workouts": 32, "nutritionLogs": 37, "sleepLogs": 39 },
    { "date": "2024-09-15", "activeUsers": 38, "totalSteps": 327600, "avgSteps": 8621, "workouts": 30, "nutritionLogs": 36, "sleepLogs": 38 },
    { "date": "2024-09-16", "activeUsers": 39, "totalSteps": 336570, "avgSteps": 8630, "workouts": 31, "nutritionLogs": 37, "sleepLogs": 39 },
    { "date": "2024-09-17", "activeUsers": 40, "totalSteps": 346400, "avgSteps": 8660, "workouts": 33, "nutritionLogs": 38, "sleepLogs": 40 },
    { "date": "2024-09-18", "activeUsers": 40, "totalSteps": 348000, "avgSteps": 8700, "workouts": 34, "nutritionLogs": 39, "sleepLogs": 40 },
    { "date": "2024-09-19", "activeUsers": 41, "totalSteps": 357070, "avgSteps": 8709, "workouts": 35, "nutritionLogs": 40, "sleepLogs": 41 },
    { "date": "2024-09-20", "activeUsers": 41, "totalSteps": 359380, "avgSteps": 8765, "workouts": 36, "nutritionLogs": 40, "sleepLogs": 41 },
    { "date": "2024-09-21", "activeUsers": 42, "totalSteps": 368460, "avgSteps": 8773, "workouts": 37, "nutritionLogs": 41, "sleepLogs": 42 },
    { "date": "2024-09-22", "activeUsers": 42, "totalSteps": 370440, "avgSteps": 8820, "workouts": 38, "nutritionLogs": 41, "sleepLogs": 42 },
    { "date": "2024-09-23", "activeUsers": 42, "totalSteps": 372960, "avgSteps": 8880, "workouts": 39, "nutritionLogs": 42, "sleepLogs": 42 },
    { "date": "2024-09-24", "activeUsers": 42, "totalSteps": 375480, "avgSteps": 8940, "workouts": 40, "nutritionLogs": 42, "sleepLogs": 42 },
    { "date": "2024-09-25", "activeUsers": 41, "totalSteps": 368460, "avgSteps": 8987, "workouts": 39, "nutritionLogs": 41, "sleepLogs": 41 },
    { "date": "2024-09-26", "activeUsers": 40, "totalSteps": 360000, "avgSteps": 9000, "workouts": 38, "nutritionLogs": 40, "sleepLogs": 40 },
    { "date": "2024-09-27", "activeUsers": 39, "totalSteps": 352260, "avgSteps": 9033, "workouts": 36, "nutritionLogs": 39, "sleepLogs": 39 },
    { "date": "2024-09-28", "activeUsers": 38, "totalSteps": 344520, "avgSteps": 9066, "workouts": 34, "nutritionLogs": 38, "sleepLogs": 38 },
    { "date": "2024-09-29", "activeUsers": 39, "totalSteps": 354510, "avgSteps": 9090, "workouts": 35, "nutritionLogs": 39, "sleepLogs": 39 },
    { "date": "2024-09-30", "activeUsers": 40, "totalSteps": 364800, "avgSteps": 9120, "workouts": 37, "nutritionLogs": 40, "sleepLogs": 40 },
    { "date": "2024-10-01", "activeUsers": 40, "totalSteps": 366000, "avgSteps": 9150, "workouts": 38, "nutritionLogs": 40, "sleepLogs": 40 },
    { "date": "2024-10-02", "activeUsers": 41, "totalSteps": 376690, "avgSteps": 9187, "workouts": 39, "nutritionLogs": 41, "sleepLogs": 41 },
    { "date": "2024-10-03", "activeUsers": 41, "totalSteps": 378420, "avgSteps": 9229, "workouts": 40, "nutritionLogs": 41, "sleepLogs": 41 },
    { "date": "2024-10-04", "activeUsers": 42, "totalSteps": 388290, "avgSteps": 9245, "workouts": 41, "nutritionLogs": 42, "sleepLogs": 42 },
    { "date": "2024-10-05", "activeUsers": 42, "totalSteps": 389760, "avgSteps": 9280, "workouts": 42, "nutritionLogs": 42, "sleepLogs": 42 },
    { "date": "2024-10-06", "activeUsers": 42, "totalSteps": 391230, "avgSteps": 9315, "workouts": 43, "nutritionLogs": 42, "sleepLogs": 42 },
    { "date": "2024-10-07", "activeUsers": 42, "totalSteps": 392700, "avgSteps": 9350, "workouts": 44, "nutritionLogs": 42, "sleepLogs": 42 },
    { "date": "2024-10-08", "activeUsers": 41, "totalSteps": 384605, "avgSteps": 9380, "workouts": 43, "nutritionLogs": 41, "sleepLogs": 41 },
    { "date": "2024-10-09", "activeUsers": 40, "totalSteps": 376000, "avgSteps": 9400, "workouts": 42, "nutritionLogs": 40, "sleepLogs": 40 },
    { "date": "2024-10-10", "activeUsers": 39, "totalSteps": 367470, "avgSteps": 9422, "workouts": 40, "nutritionLogs": 39, "sleepLogs": 39 },
    { "date": "2024-10-11", "activeUsers": 38, "totalSteps": 358880, "avgSteps": 9444, "workouts": 38, "nutritionLogs": 38, "sleepLogs": 38 },
    { "date": "2024-10-12", "activeUsers": 39, "totalSteps": 369330, "avgSteps": 9470, "workouts": 39, "nutritionLogs": 39, "sleepLogs": 39 },
    { "date": "2024-10-13", "activeUsers": 40, "totalSteps": 380000, "avgSteps": 9500, "workouts": 41, "nutritionLogs": 40, "sleepLogs": 40 },
    { "date": "2024-10-14", "activeUsers": 40, "totalSteps": 381200, "avgSteps": 9530, "workouts": 42, "nutritionLogs": 40, "sleepLogs": 40 },
    { "date": "2024-10-15", "activeUsers": 41, "totalSteps": 391970, "avgSteps": 9560, "workouts": 43, "nutritionLogs": 41, "sleepLogs": 41 },
    { "date": "2024-10-16", "activeUsers": 41, "totalSteps": 393490, "avgSteps": 9597, "workouts": 44, "nutritionLogs": 41, "sleepLogs": 41 },
    { "date": "2024-10-17", "activeUsers": 42, "totalSteps": 403830, "avgSteps": 9615, "workouts": 45, "nutritionLogs": 42, "sleepLogs": 42 },
    { "date": "2024-10-18", "activeUsers": 42, "totalSteps": 405240, "avgSteps": 9649, "workouts": 46, "nutritionLogs": 42, "sleepLogs": 42 },
    { "date": "2024-10-19", "activeUsers": 42, "totalSteps": 406650, "avgSteps": 9682, "workouts": 47, "nutritionLogs": 42, "sleepLogs": 42 },
    { "date": "2024-10-20", "activeUsers": 42, "totalSteps": 408060, "avgSteps": 9716, "workouts": 48, "nutritionLogs": 42, "sleepLogs": 42 },
    { "date": "2024-10-21", "activeUsers": 41, "totalSteps": 399650, "avgSteps": 9748, "workouts": 47, "nutritionLogs": 41, "sleepLogs": 41 },
    { "date": "2024-10-22", "activeUsers": 40, "totalSteps": 390400, "avgSteps": 9760, "workouts": 46, "nutritionLogs": 40, "sleepLogs": 40 },
    { "date": "2024-10-23", "activeUsers": 39, "totalSteps": 381420, "avgSteps": 9780, "workouts": 44, "nutritionLogs": 39, "sleepLogs": 39 },
    { "date": "2024-10-24", "activeUsers": 38, "totalSteps": 372440, "avgSteps": 9801, "workouts": 42, "nutritionLogs": 38, "sleepLogs": 38 },
    { "date": "2024-10-25", "activeUsers": 39, "totalSteps": 383370, "avgSteps": 9830, "workouts": 43, "nutritionLogs": 39, "sleepLogs": 39 },
    { "date": "2024-10-26", "activeUsers": 40, "totalSteps": 394400, "avgSteps": 9860, "workouts": 45, "nutritionLogs": 40, "sleepLogs": 40 },
    { "date": "2024-10-27", "activeUsers": 40, "totalSteps": 395600, "avgSteps": 9890, "workouts": 46, "nutritionLogs": 40, "sleepLogs": 40 },
    { "date": "2024-10-28", "activeUsers": 41, "totalSteps": 406330, "avgSteps": 9910, "workouts": 47, "nutritionLogs": 41, "sleepLogs": 41 },
    { "date": "2024-10-29", "activeUsers": 41, "totalSteps": 407770, "avgSteps": 9945, "workouts": 48, "nutritionLogs": 41, "sleepLogs": 41 },
    { "date": "2024-10-30", "activeUsers": 42, "totalSteps": 418320, "avgSteps": 9960, "workouts": 49, "nutritionLogs": 42, "sleepLogs": 42 },
    { "date": "2024-10-31", "activeUsers": 42, "totalSteps": 419580, "avgSteps": 9990, "workouts": 50, "nutritionLogs": 42, "sleepLogs": 42 },
    { "date": "2024-11-01", "activeUsers": 42, "totalSteps": 420840, "avgSteps": 10020, "workouts": 51, "nutritionLogs": 42, "sleepLogs": 42 },
    { "date": "2024-11-02", "activeUsers": 42, "totalSteps": 422100, "avgSteps": 10050, "workouts": 52, "nutritionLogs": 42, "sleepLogs": 42 },
    { "date": "2024-11-03", "activeUsers": 41, "totalSteps": 413230, "avgSteps": 10079, "workouts": 51, "nutritionLogs": 41, "sleepLogs": 41 },
    { "date": "2024-11-04", "activeUsers": 40, "totalSteps": 404000, "avgSteps": 10100, "workouts": 50, "nutritionLogs": 40, "sleepLogs": 40 },
    { "date": "2024-11-05", "activeUsers": 39, "totalSteps": 394770, "avgSteps": 10122, "workouts": 48, "nutritionLogs": 39, "sleepLogs": 39 },
    { "date": "2024-11-06", "activeUsers": 38, "totalSteps": 385540, "avgSteps": 10146, "workouts": 46, "nutritionLogs": 38, "sleepLogs": 38 },
    { "date": "2024-11-07", "activeUsers": 39, "totalSteps": 396630, "avgSteps": 10170, "workouts": 47, "nutritionLogs": 39, "sleepLogs": 39 },
    { "date": "2024-11-08", "activeUsers": 40, "totalSteps": 407800, "avgSteps": 10195, "workouts": 49, "nutritionLogs": 40, "sleepLogs": 40 },
    { "date": "2024-11-09", "activeUsers": 40, "totalSteps": 408800, "avgSteps": 10220, "workouts": 50, "nutritionLogs": 40, "sleepLogs": 40 },
    { "date": "2024-11-10", "activeUsers": 41, "totalSteps": 420050, "avgSteps": 10245, "workouts": 51, "nutritionLogs": 41, "sleepLogs": 41 },
    { "date": "2024-11-11", "activeUsers": 41, "totalSteps": 421290, "avgSteps": 10275, "workouts": 52, "nutritionLogs": 41, "sleepLogs": 41 },
    { "date": "2024-11-12", "activeUsers": 42, "totalSteps": 432600, "avgSteps": 10300, "workouts": 53, "nutritionLogs": 42, "sleepLogs": 42 },
    { "date": "2024-11-13", "activeUsers": 42, "totalSteps": 433650, "avgSteps": 10325, "workouts": 54, "nutritionLogs": 42, "sleepLogs": 42 },
    { "date": "2024-11-14", "activeUsers": 42, "totalSteps": 434700, "avgSteps": 10350, "workouts": 55, "nutritionLogs": 42, "sleepLogs": 42 },
    { "date": "2024-11-15", "activeUsers": 42, "totalSteps": 435750, "avgSteps": 10375, "workouts": 56, "nutritionLogs": 42, "sleepLogs": 42 },
    { "date": "2024-11-16", "activeUsers": 43, "totalSteps": 447200, "avgSteps": 10400, "workouts": 57, "nutritionLogs": 43, "sleepLogs": 43 },
    { "date": "2024-11-17", "activeUsers": 44, "totalSteps": 459800, "avgSteps": 10450, "workouts": 58, "nutritionLogs": 44, "sleepLogs": 44 },
    { "date": "2024-11-18", "activeUsers": 45, "totalSteps": 472500, "avgSteps": 10500, "workouts": 59, "nutritionLogs": 45, "sleepLogs": 45 }
  ],
  "featureUsage": {
    "workoutsLogged": { "count": 2847, "percentage": 35 },
    "nutritionTracking": { "count": 2282, "percentage": 28 },
    "sleepLogging": { "count": 1792, "percentage": 22 },
    "challenges": { "count": 1222, "percentage": 15 }
  },
  "departmentParticipation": [
    { "id": "sales", "name": "Sales", "total": 10, "active": 8, "rate": 85 },
    { "id": "creative", "name": "Creative", "total": 20, "active": 18, "rate": 82 },
    { "id": "production", "name": "Production", "total": 15, "active": 12, "rate": 76 },
    { "id": "admin", "name": "Admin", "total": 5, "active": 4, "rate": 70 }
  ]
}
